sparky/__init__.py
sparky/cli.py
sparky/core/__init__.py
sparky/core/action_queue.py
sparky/core/analytics_engine.py
sparky/core/connection.py
sparky/core/data_collector.py
sparky/core/motion.py
sparky/core/safety_manager.py
sparky/core/stream_processor.py
sparky/interfaces.py
sparky/robot.py
sparky/safety/emergency_response.py
sparky/safety/environmental_safety.py
sparky/safety/fall_detection.py
sparky/utils/__init__.py
sparky/utils/banner.py
sparky/utils/constants.py
sparky/utils/exceptions.py
go2_sparky-0.0.2.dist-info/METADATA
go2_sparky-0.0.2.dist-info/WHEEL
go2_sparky-0.0.2.dist-info/entry_points.txt
go2_sparky-0.0.2.dist-info/RECORD
