Metadata-Version: 2.3
Name: go2-sparky
Version: 0.0.2
Summary: 🤖 Comprehensive Go2 Robot Control Package
Author: Ranga Reddy Nukala
Author-email: itsmerr17@gmail.com
Requires-Python: >=3.11
Classifier: Programming Language :: Python :: 3
Classifier: Programming Language :: Python :: 3.11
Classifier: Programming Language :: Python :: 3.12
Classifier: Programming Language :: Python :: 3.13
Provides-Extra: all
Provides-Extra: cli
Provides-Extra: dev
Requires-Dist: deptry (>=0.12.0) ; extra == "dev" or extra == "all"
Requires-Dist: go2-webrtc-connect (>=0.2.0,<0.3.0)
Requires-Dist: mypy (>=1.7.0) ; extra == "dev" or extra == "all"
Requires-Dist: pytest (>=7.4.0) ; extra == "dev" or extra == "all"
Requires-Dist: pytest-cov (>=4.1.0) ; extra == "dev" or extra == "all"
Requires-Dist: pytest-html (>=4.1.0) ; extra == "dev" or extra == "all"
Requires-Dist: rich (>=14.1.0,<15.0.0) ; extra == "cli" or extra == "all"
Requires-Dist: ruff (>=0.1.0) ; extra == "dev" or extra == "all"
Requires-Dist: safety (>=2.3.0) ; extra == "dev" or extra == "all"
Requires-Dist: typer[all] (>=0.16.0,<0.17.0) ; extra == "cli" or extra == "all"
